snowflake_dbml/__init__.py
snowflake_dbml/config.py
snowflake_dbml/generator.py
snowflake_dbml/version.py
snowflake_dbml_generator-0.1.2.dist-info/LICENSE
snowflake_dbml_generator-0.1.2.dist-info/METADATA
snowflake_dbml_generator-0.1.2.dist-info/WHEEL
snowflake_dbml_generator-0.1.2.dist-info/entry_points.txt
snowflake_dbml_generator-0.1.2.dist-info/top_level.txt
snowflake_dbml_generator-0.1.2.dist-info/RECORD
