Metadata-Version: 2.1
Name: snowflake-dbml-generator
Version: 0.1.2
Summary: Automatically generate DBML files from Snowflake databases.
Home-page: https://github.com/ryanrozich/snowflake-dbml-generator
Author: Ryan Rozich
Author-email: github@rozich.com
Classifier: Programming Language :: Python :: 3
Classifier: License :: OSI Approved :: MIT License
License-File: LICENSE
Requires-Dist: snowflake-connector-python >=3.9.0
Requires-Dist: python-dotenv >=1.0.1
Requires-Dist: pydbml >=0.1.11
